digitaleye_msgs/__init__.py
digitaleye_msgs/msg/_AccessSchedule.py
digitaleye_msgs/msg/_Action.py
digitaleye_msgs/msg/_ActionStatus.py
digitaleye_msgs/msg/_Allocation.py
digitaleye_msgs/msg/_Block.py
digitaleye_msgs/msg/_Booking.py
digitaleye_msgs/msg/_BookingActions.py
digitaleye_msgs/msg/_BookingAllocations.py
digitaleye_msgs/msg/_BookingOption.py
digitaleye_msgs/msg/_BookingStatus.py
digitaleye_msgs/msg/_Breach.py
digitaleye_msgs/msg/_BreachPicture.py
digitaleye_msgs/msg/_C2details.py
digitaleye_msgs/msg/_ComponentState.py
digitaleye_msgs/msg/_Conformance.py
digitaleye_msgs/msg/_ConformanceStatus.py
digitaleye_msgs/msg/_ConformanceUavStatus.py
digitaleye_msgs/msg/_Constants.py
digitaleye_msgs/msg/_ConstantsAllocations.py
digitaleye_msgs/msg/_ConstantsBookings.py
digitaleye_msgs/msg/_DigitalEyeStatus.py
digitaleye_msgs/msg/_ExtAction.py
digitaleye_msgs/msg/_Flightpath.py
digitaleye_msgs/msg/_Flightpoint.py
digitaleye_msgs/msg/_GNSSPosition.py
digitaleye_msgs/msg/_GNSSState.py
digitaleye_msgs/msg/_IMUValue.py
digitaleye_msgs/msg/_LayoutDefinition.py
digitaleye_msgs/msg/_MASDefinition.py
digitaleye_msgs/msg/_MGSDefinition.py
digitaleye_msgs/msg/_MGSStatus.py
digitaleye_msgs/msg/_MVSControl.py
digitaleye_msgs/msg/_Metric.py
digitaleye_msgs/msg/_MvSafetyStatus.py
digitaleye_msgs/msg/_Object.py
digitaleye_msgs/msg/_ObjectList.py
digitaleye_msgs/msg/_Pause.py
digitaleye_msgs/msg/_Pole.py
digitaleye_msgs/msg/_PolePose.py
digitaleye_msgs/msg/_Position.py
digitaleye_msgs/msg/_SafetyStatus.py
digitaleye_msgs/msg/_Sector.py
digitaleye_msgs/msg/_SectorPicture.py
digitaleye_msgs/msg/_Sensor.py
digitaleye_msgs/msg/_SensorPose.py
digitaleye_msgs/msg/_State.py
digitaleye_msgs/msg/_SystemCommand.py
digitaleye_msgs/msg/_SystemConfiguration.py
digitaleye_msgs/msg/_SystemNotification.py
digitaleye_msgs/msg/_SystemState.py
digitaleye_msgs/msg/_SystemTransition.py
digitaleye_msgs/msg/_TimeSlot.py
digitaleye_msgs/msg/_UavExtReport.py
digitaleye_msgs/msg/_UavExtReportList.py
digitaleye_msgs-1.11.0.dist-info/METADATA
digitaleye_msgs-1.11.0.dist-info/WHEEL
digitaleye_msgs-1.11.0.dist-info/top_level.txt
digitaleye_msgs-1.11.0.dist-info/RECORD
