Metadata-Version: 2.1
Name: digitaleye-msgs
Version: 1.11.0
Summary: Python ROS Message for the PORTAL system
Home-page: UNKNOWN
Author: Slink Tech
Author-email: sven@slink-tech.co.uk
License: UNKNOWN
Platform: UNKNOWN
Classifier: Programming Language :: Python :: 3
Classifier: License :: OSI Approved :: MIT License
Classifier: Operating System :: OS Independent
Requires-Python: >=3.6
